needle/__init__.py
needle/spec/__init__.py
needle/spec/events.py
needle/spec/events.stitcher.yaml
needle/spec/protocols.py
needle/spec/protocols.stitcher.yaml
pyneedle_spec-0.1.5.dist-info/METADATA
pyneedle_spec-0.1.5.dist-info/WHEEL
pyneedle_spec-0.1.5.dist-info/RECORD
